{
  "slug": "ao-no-orchestra",
  "clean_title": "Ao no Orchestra",
  "raw_name": "انمي Ao no Orchestra",
  "category": "anime",
  "category_label": "أنمي",
  "poster": "https://pub-7bd753a4463049929e562aa677ad4251.r2.dev/anime/ao-no-orchestra.png",
  "note": "تم إثراء بيانات هذا الأنمي من ملف Witanime مع استبعاد السيرفرات التالفة.",
  "matched_poster": true,
  "seasons_count": 1,
  "episodes_count": 13,
  "seasons": [
    {
      "season": 1,
      "episodes_count": 13,
      "episodes": [
        {
          "episode": 1,
          "title": "الحلقة 1",
          "servers": [
            {
              "id": 1,
              "label": "videa",
              "url": "https://videa.hu/player?v=joOwpiNk2TyCF943"
            },
            {
              "id": 2,
              "label": "mega - SD",
              "url": "https://mega.nz/embed/oioG0AgC#Ud3xtuALrt_PqIJ7eFaDgo7b2tWIR8yDvtLt_I-fRyk"
            },
            {
              "id": 3,
              "label": "videa - FHD",
              "url": "https://videa.hu/player?v=3TqOq3tWgLhvgvuK"
            }
          ],
          "overview": null,
          "air_date": "2023-04-09",
          "runtime": 25,
          "tmdb_episode_id": 3658656,
          "tmdb_still_path": "/jMXdLKbJ9FYsztdQZ9EbuXkr6dA.jpg"
        },
        {
          "episode": 2,
          "title": "الحلقة 2",
          "servers": [
            {
              "id": 1,
              "label": "videa",
              "url": "https://videa.hu/player?v=H0FwRxcGBo9je6Jz"
            },
            {
              "id": 2,
              "label": "dailymotion",
              "url": "https://www.dailymotion.com/embed/video/x8k64jo"
            },
            {
              "id": 3,
              "label": "videa - FHD",
              "url": "https://videa.hu/player?v=IkBvKdUlKUcDPXEC"
            },
            {
              "id": 4,
              "label": "dailymotion - FHD",
              "url": "https://www.dailymotion.com/embed/video/x8k64o1"
            }
          ],
          "overview": null,
          "air_date": "2023-04-16",
          "runtime": 25,
          "tmdb_episode_id": 4317686,
          "tmdb_still_path": "/tiMxK9Btoek7ShL5umIABISixhS.jpg"
        },
        {
          "episode": 3,
          "title": "الحلقة 3",
          "servers": [
            {
              "id": 1,
              "label": "videa",
              "url": "https://videa.hu/player?v=xWIopqBuPkWVX4Ye"
            },
            {
              "id": 2,
              "label": "mega - SD",
              "url": "https://mega.nz/embed/T2RwTa4b#hn-XRJ8BXK5z_W5p0ctE1Acy98HePbNyorE5nU4RK8k"
            },
            {
              "id": 3,
              "label": "videa - FHD",
              "url": "https://videa.hu/player?v=711PLIhXQr1aGR89"
            }
          ],
          "overview": null,
          "air_date": "2023-04-23",
          "runtime": 25,
          "tmdb_episode_id": 4317687,
          "tmdb_still_path": "/cJQqjUJI6dkgYHUHpG9UGB3tpym.jpg"
        },
        {
          "episode": 4,
          "title": "الحلقة 4",
          "servers": [
            {
              "id": 1,
              "label": "videa",
              "url": "https://videa.hu/player?v=CyzzLVreh8f7y3Qp"
            },
            {
              "id": 2,
              "label": "videa - FHD",
              "url": "https://videa.hu/player?v=U0zTZyMXZ1LxeRdP"
            }
          ],
          "overview": null,
          "air_date": "2023-04-30",
          "runtime": 25,
          "tmdb_episode_id": 4317688,
          "tmdb_still_path": "/qFZdYXtUpYYOlUKnJZJbc02WnwZ.jpg"
        },
        {
          "episode": 5,
          "title": "الحلقة 5",
          "servers": [
            {
              "id": 1,
              "label": "videa",
              "url": "https://www.mediafire.com/file/mn9924t4tvaqd0h/%5BWitanime.com%5D+ANO+EP+05+HD.zip/file"
            },
            {
              "id": 2,
              "label": "dailymotion",
              "url": "https://www.dailymotion.com/embed/video/x8krp7b"
            },
            {
              "id": 3,
              "label": "videa - FHD",
              "url": "https://videa.hu/player?v=GEgZyrs23eEtIV1l"
            },
            {
              "id": 4,
              "label": "dailymotion - FHD",
              "url": "https://www.dailymotion.com/embed/video/x8krpky"
            }
          ],
          "overview": null,
          "air_date": "2023-05-07",
          "runtime": 25,
          "tmdb_episode_id": 4317689,
          "tmdb_still_path": "/lnNYP7r7aKVMJPmoqC85cgeCtPD.jpg"
        },
        {
          "episode": 6,
          "title": "الحلقة 6",
          "servers": [
            {
              "id": 1,
              "label": "videa",
              "url": "https://videa.hu/player?v=a9p2472zqm90XRyM"
            },
            {
              "id": 2,
              "label": "videa - FHD",
              "url": "https://videa.hu/player?v=OsvfhemeHGQmkXso"
            }
          ],
          "overview": null,
          "air_date": "2023-05-14",
          "runtime": 25,
          "tmdb_episode_id": 4317690,
          "tmdb_still_path": "/eHsUEsCbHorahKWGUc4u02lcCgq.jpg"
        },
        {
          "episode": 7,
          "title": "الحلقة 7",
          "servers": [
            {
              "id": 1,
              "label": "videa",
              "url": "https://videa.hu/player?v=pamYPBLgxqRANGS9"
            },
            {
              "id": 2,
              "label": "videa - FHD",
              "url": "https://videa.hu/player?v=28WCHOYEtnnFoXu9"
            }
          ],
          "overview": null,
          "air_date": "2023-05-21",
          "runtime": 25,
          "tmdb_episode_id": 4317691,
          "tmdb_still_path": "/xfldXKaWcFen5JN9olnQ9aUoKdA.jpg"
        },
        {
          "episode": 8,
          "title": "الحلقة 8",
          "servers": [
            {
              "id": 1,
              "label": "videa",
              "url": "https://videa.hu/player?v=ZYr6phyWYUBCRjQ0"
            },
            {
              "id": 2,
              "label": "dailymotion",
              "url": "https://www.dailymotion.com/embed/video/x8ldrjr"
            },
            {
              "id": 3,
              "label": "videa - FHD",
              "url": "https://videa.hu/player?v=zwivTmM3BR8Ax09j"
            },
            {
              "id": 4,
              "label": "dailymotion - FHD",
              "url": "https://www.dailymotion.com/embed/video/x8ldrsy"
            }
          ],
          "overview": null,
          "air_date": "2023-05-28",
          "runtime": 25,
          "tmdb_episode_id": 4317692,
          "tmdb_still_path": "/kaNRda2ntCT7GL43E1MYU4gLh9g.jpg"
        },
        {
          "episode": 9,
          "title": "الحلقة 9",
          "servers": [
            {
              "id": 1,
              "label": "videa",
              "url": "https://videa.hu/player?v=zGU5zfNr6A9YMlh9"
            },
            {
              "id": 2,
              "label": "videa - FHD",
              "url": "https://videa.hu/player?v=3W3u4YNBGmn1lvyd"
            }
          ],
          "overview": null,
          "air_date": "2023-06-04",
          "runtime": 25,
          "tmdb_episode_id": 4317693,
          "tmdb_still_path": "/8qbx3wRjGN7lmfoARZ9SSkIRuvT.jpg"
        },
        {
          "episode": 10,
          "title": "الحلقة 10",
          "servers": [
            {
              "id": 1,
              "label": "videa",
              "url": "https://videa.hu/player?v=6NK9RVFVOFe0aaJJ"
            },
            {
              "id": 2,
              "label": "videa - FHD",
              "url": "https://videa.hu/player?v=4Tdw7kO9j7FvaG8U"
            }
          ],
          "overview": null,
          "air_date": "2023-06-11",
          "runtime": 25,
          "tmdb_episode_id": 4317694,
          "tmdb_still_path": "/mjf1W761rxISxM4JNkuwrvK2kC5.jpg"
        },
        {
          "episode": 11,
          "title": "الحلقة 11",
          "servers": [
            {
              "id": 1,
              "label": "videa",
              "url": "https://videa.hu/player?v=ntmmsEs071MAw8R2"
            },
            {
              "id": 2,
              "label": "videa - FHD",
              "url": "https://videa.hu/player?v=XjP6cZn1Rx64PIc9"
            }
          ],
          "overview": null,
          "air_date": "2023-06-18",
          "runtime": 25,
          "tmdb_episode_id": 4317695,
          "tmdb_still_path": "/eZg3W7SqxzfzUbIellaN0k4Je79.jpg"
        },
        {
          "episode": 12,
          "title": "الحلقة 12",
          "servers": [
            {
              "id": 1,
              "label": "videa",
              "url": "https://videa.hu/player?v=6LaOk5RLliuy2dFZ"
            },
            {
              "id": 2,
              "label": "videa - FHD",
              "url": "https://videa.hu/player?v=ryPNVdroCo6ATGIP"
            }
          ],
          "overview": null,
          "air_date": "2023-06-25",
          "runtime": 25,
          "tmdb_episode_id": 4317696,
          "tmdb_still_path": "/yN6bRERp18VojkfY3XgYjQUKTp1.jpg"
        },
        {
          "episode": 13,
          "title": "الحلقة 13",
          "servers": [
            {
              "id": 1,
              "label": "videa",
              "url": "https://videa.hu/player?v=AFYbpZqUEeiXOein"
            },
            {
              "id": 2,
              "label": "dailymotion",
              "url": "https://www.dailymotion.com/embed/video/x8mce18"
            },
            {
              "id": 3,
              "label": "videa - FHD",
              "url": "https://videa.hu/player?v=b4q2IUXQjstByWn8"
            }
          ],
          "overview": null,
          "air_date": "2023-07-02",
          "runtime": 25,
          "tmdb_episode_id": 4317697,
          "tmdb_still_path": "/9Jz4hAfG3WJCz82fhASfWdWIzEp.jpg"
        }
      ]
    }
  ],
  "description": "يدور أنمي Ao no Orchestra ضمن أجواء رسوم متحركة، دراما، ويعتمد على حكاية تتطور عبر الشخصيات والمواجهات بدل الاكتفاء بفكرة واحدة. بدأ عرض العمل عام 2023، وتوضح بيانات TMDB أنه يضم 2 موسم و45 حلقة. تبدأ قصة Ao no Orchestra من تفاصيل يومية داخل المدرسة أو الحياة القريبة من الشخصيات وما تصنعه من صداقات وقرارات. ينتمي العمل إلى أجواء موسيقى، مدرسي، دراما، لذلك يتقدم بهدوء عبر مواقف متتابعة تكشف طباع كل شخصية. وتوضح بيانات المصدر أن حالة العرض هي يعرض الان. صفحة CINMAPRO ترتب 1 موسم و13 حلقة لتبدأ من الحلقة المناسبة دون بحث طويل. يناسب من يحب الحكايات الهادئة التي تعتمد على العلاقات أكثر من الصخب.",
  "url": "/anime/ao-no-orchestra",
  "story": "يدور أنمي Ao no Orchestra ضمن أجواء رسوم متحركة، دراما، ويعتمد على حكاية تتطور عبر الشخصيات والمواجهات بدل الاكتفاء بفكرة واحدة. بدأ عرض العمل عام 2023، وتوضح بيانات TMDB أنه يضم 2 موسم و45 حلقة. تبدأ قصة Ao no Orchestra من تفاصيل يومية داخل المدرسة أو الحياة القريبة من الشخصيات وما تصنعه من صداقات وقرارات. ينتمي العمل إلى أجواء موسيقى، مدرسي، دراما، لذلك يتقدم بهدوء عبر مواقف متتابعة تكشف طباع كل شخصية. وتوضح بيانات المصدر أن حالة العرض هي يعرض الان. صفحة CINMAPRO ترتب 1 موسم و13 حلقة لتبدأ من الحلقة المناسبة دون بحث طويل. يناسب من يحب الحكايات الهادئة التي تعتمد على العلاقات أكثر من الصخب.",
  "year": "2023",
  "quality": "FHD",
  "duration": null,
  "language": "اليابانية",
  "country": "اليابان",
  "director": null,
  "stars": "Shoya Chiba، Shimba Tsuchiya، Ai Kakuma، Minako Sato",
  "genre": "أنمي، رسوم متحركة، دراما",
  "trailerId": null,
  "rating": "7.0",
  "imdb_rating": "7.0",
  "seoContent": {
    "generatedAt": "2026-05-18",
    "arabicTitle": "Ao no Orchestra",
    "mainDescription": "يدور أنمي Ao no Orchestra ضمن أجواء رسوم متحركة، دراما، ويعتمد على حكاية تتطور عبر الشخصيات والمواجهات بدل الاكتفاء بفكرة واحدة. بدأ عرض العمل عام 2023، وتوضح بيانات TMDB أنه يضم 2 موسم و45 حلقة. تبدأ قصة Ao no Orchestra من تفاصيل يومية داخل المدرسة أو الحياة القريبة من الشخصيات وما تصنعه من صداقات وقرارات. ينتمي العمل إلى أجواء موسيقى، مدرسي، دراما، لذلك يتقدم بهدوء عبر مواقف متتابعة تكشف طباع كل شخصية. وتوضح بيانات المصدر أن حالة العرض هي يعرض الان. صفحة CINMAPRO ترتب 1 موسم و13 حلقة لتبدأ من الحلقة المناسبة دون بحث طويل. يناسب من يحب الحكايات الهادئة التي تعتمد على العلاقات أكثر من الصخب.",
    "metaDescription": "Ao no Orchestra أنمي 2023 | يدور أنمي Ao no Orchestra ضمن أجواء رسوم متحركة | شاهد HD على CINMAPRO",
    "highlights": "تم تحديث بيانات Ao no Orchestra من TMDB مع ربط المواسم المتاحة وترتيب الحلقات داخل CINMAPRO. تظهر الصفحة القصة والتصنيفات والتقييم وروابط المشاهدة بدون خلط بين المواسم.",
    "beforeWatchingPoints": [
      "ابدأ من الحلقة الأولى إذا كان الأنمي قصصيًا أو يعتمد على تطور الشخصيات.",
      "اختر السيرفرات الأولى لأنها أضيفت من القائمة الأحدث بعد تنظيف الروابط التالفة.",
      "المشاهدة بجودة عالية أفضل خصوصًا في الأعمال التي تعتمد على الحركة أو التفاصيل البصرية."
    ],
    "sources": {
      "tmdb": "https://www.themoviedb.org/tv/197368"
    }
  },
  "tmdb_id": 197368,
  "tmdb_url": "https://www.themoviedb.org/tv/197368",
  "original_title": "青のオーケストラ"
}