{
  "slug": "my-sons-deception-2024-مترجم-اون-لاين",
  "clean_title": "My Son’s Deception 2024 مترجم اون لاين",
  "raw_name": "فيلم My Son’s Deception 2024 مترجم اون لاين",
  "category": "movie",
  "category_label": "فيلم",
  "poster": "/images/movie/my-sons-deception-2024-مترجم-اون-لاين.jpg",
  "note": "بوستر الفيلم",
  "matched_poster": true,
  "seasons_count": 1,
  "episodes_count": 1,
  "seasons": [
    {
      "season": 1,
      "episodes_count": 1,
      "episodes": [
        {
          "episode": 1,
          "title": "الحلقة 1",
          "servers": [
            {
              "id": 1,
              "label": "سيرفر 1",
              "url": "https://vidtube.one/embed-ijs0bl5s21d4.html"
            },
            {
              "id": 2,
              "label": "سيرفر 2",
              "url": "https://updown.icu/embed-odjd3l8g6ec7-1280x640.html"
            },
            {
              "id": 3,
              "label": "سيرفر 3",
              "url": "https://streamwish.fun/e/0nz22jslqadb"
            },
            {
              "id": 4,
              "label": "سيرفر 4",
              "url": "https://d0o0d.com/e/ypyi1vy5pw75"
            },
            {
              "id": 5,
              "label": "سيرفر 5",
              "url": "https://earnvids.xyz/v/nhvqkm749fm0"
            },
            {
              "id": 6,
              "label": "سيرفر 6",
              "url": "https://ok.ru/videoembed/7401537145541"
            },
            {
              "id": 7,
              "label": "سيرفر 7",
              "url": "https://streamtape.cc/e/VPRvZeQPJ2FP0m"
            },
            {
              "id": 8,
              "label": "سيرفر 8",
              "url": "https://luluvdo.com/e/49nfgrv14ag9"
            }
          ]
        }
      ]
    }
  ],
  "description": "Jackson Dawes يواجه حدثًا يغيّر مسار الحكاية في My Son’s Deception، حيث تتحرك القصة داخل أجواء إثارة، فيلم تلفازي وتربط الخطر باختيارات الشخصيات لا بالمشهد السريع وحده. صدر الفيلم عام 2024 ضمن إنتاج كندا، وتساعد بيانات TMDB على توضيح سياقه وطاقمه وتصنيفه. صفحة CINMAPRO تعرض القصة والمعلومات الأساسية والتريلر وروابط المشاهدة بترتيب مباشر.",
  "url": "/movie/my-sons-deception-2024-مترجم-اون-لاين",
  "story": "Jackson Dawes يواجه حدثًا يغيّر مسار الحكاية في My Son’s Deception، حيث تتحرك القصة داخل أجواء إثارة، فيلم تلفازي وتربط الخطر باختيارات الشخصيات لا بالمشهد السريع وحده. صدر الفيلم عام 2024 ضمن إنتاج كندا، وتساعد بيانات TMDB على توضيح سياقه وطاقمه وتصنيفه. صفحة CINMAPRO تعرض القصة والمعلومات الأساسية والتريلر وروابط المشاهدة بترتيب مباشر.",
  "year": "2024",
  "quality": "1080p WEB-DL",
  "duration": null,
  "language": "الإنجليزية",
  "country": "كندا",
  "director": "Meeshelle Neal",
  "stars": "Tyssen Smith، Kate Drummond، Carson MacCormac، Brennan Clost، Matt Wells، Gita Miller",
  "genre": "إثارة، فيلم تلفازي",
  "tmdb_id": 1266392,
  "tmdb_url": "https://www.themoviedb.org/movie/1266392",
  "original_title": "My Son's Deception",
  "rating": "4.6",
  "imdb_rating": "4.6",
  "trailerId": "dXv9bCl64j0",
  "seoContent": {
    "generatedAt": "2026-05-26",
    "mainDescription": "Jackson Dawes يواجه حدثًا يغيّر مسار الحكاية في My Son’s Deception، حيث تتحرك القصة داخل أجواء إثارة، فيلم تلفازي وتربط الخطر باختيارات الشخصيات لا بالمشهد السريع وحده. صدر الفيلم عام 2024 ضمن إنتاج كندا، وتساعد بيانات TMDB على توضيح سياقه وطاقمه وتصنيفه. صفحة CINMAPRO تعرض القصة والمعلومات الأساسية والتريلر وروابط المشاهدة بترتيب مباشر.",
    "metaDescription": "My Son's Deception My Son’s Deception فيلم 2024 | Jackson Dawes يواجه حدثًا يغيّر مسار الحكاية في My Son’s Deception | شاهد مترجم HD على CINMAPRO",
    "highlights": "تم تحديث بيانات My Son’s Deception من TMDB مع توضيح القصة والطاقم والتصنيف والتريلر عند توفره. تساعد الصفحة على فهم أجواء الفيلم قبل الانتقال إلى المشاهدة.",
    "sources": {
      "tmdb": "https://www.themoviedb.org/movie/1266392"
    }
  }
}
