{
  "slug": "poisoned-the-dirty-truth-about-your-food-2023-مترجم-اون-لاين",
  "clean_title": "Poisoned: The Dirty Truth About Your Food 2023 مترجم اون لاين",
  "raw_name": "فيلم Poisoned: The Dirty Truth About Your Food 2023 مترجم اون لاين",
  "category": "movie",
  "category_label": "فيلم",
  "poster": "/images/movie/poisoned-the-dirty-truth-about-your-food-2023-مترجم-اون-لاين.jpg",
  "note": "بوستر الفيلم",
  "matched_poster": true,
  "seasons_count": 1,
  "episodes_count": 1,
  "seasons": [
    {
      "season": 1,
      "episodes_count": 1,
      "episodes": [
        {
          "episode": 1,
          "title": "الحلقة 1",
          "servers": [
            {
              "id": 1,
              "label": "سيرفر 1",
              "url": "https://vidtube.pro/embed-yflp2zg7ivx5.html"
            },
            {
              "id": 2,
              "label": "سيرفر 2",
              "url": "https://updown.icu/embed-onitsh31ftjh-1280x640.html"
            },
            {
              "id": 3,
              "label": "سيرفر 3",
              "url": "https://streamwish.fun/e/l26sj7ou2brw"
            },
            {
              "id": 4,
              "label": "سيرفر 4",
              "url": "https://d0o0d.com/e/2goxl2ft310r"
            },
            {
              "id": 5,
              "label": "سيرفر 5",
              "url": "https://ok.ru/videoembed/6110152559301"
            },
            {
              "id": 6,
              "label": "سيرفر 6",
              "url": "https://uptostream.com/iframe/pvcn6bpq6zky"
            }
          ]
        }
      ]
    }
  ],
  "description": "يستعرض هذا الوثائقي المثير مشكلة تفشّي الأمراض المميتة المنتقلة عن طريق الغذاء في \"الولايات المتحدة\"، وذلك من خلال مقابلات كاشفة للحقيقة مع خبراء وعائلات الضحايا.",
  "url": "/movie/poisoned-the-dirty-truth-about-your-food-2023-مترجم-اون-لاين",
  "story": "يستعرض هذا الوثائقي المثير مشكلة تفشّي الأمراض المميتة المنتقلة عن طريق الغذاء في \"الولايات المتحدة\"، وذلك من خلال مقابلات كاشفة للحقيقة مع خبراء وعائلات الضحايا.",
  "year": "2023",
  "quality": "720p WEB-DL",
  "duration": "83 دقيقة",
  "language": "الإنجليزية",
  "country": "الولايات المتحدة",
  "director": "Stephanie Soechtig",
  "stars": "Bill Marler، Darin Detwiler، Dr. John Kobayashi، Lance Price, Ph.D.، Robert Nugent، Vicki Detwiler",
  "genre": "وثائقي، جريمة",
  "tmdb_id": 1115191,
  "tmdb_url": "https://www.themoviedb.org/movie/1115191",
  "original_title": "Poisoned: The Dirty Truth About Your Food",
  "rating": "7.1",
  "imdb_rating": "7.1",
  "trailerId": "YZcyMgdWmPg",
  "seoContent": {
    "generatedAt": "2026-05-26",
    "mainDescription": "يستعرض هذا الوثائقي المثير مشكلة تفشّي الأمراض المميتة المنتقلة عن طريق الغذاء في \"الولايات المتحدة\"، وذلك من خلال مقابلات كاشفة للحقيقة مع خبراء وعائلات الضحايا.",
    "metaDescription": "Poisoned: The Dirty Truth About Your Food Poisoned: The Dirty Truth About Your Food فيلم 2023 | يستعرض هذا الوثائقي المثير مشكلة تفشّي الأمراض المميتة…",
    "highlights": "تم تحديث بيانات Poisoned: The Dirty Truth About Your Food من TMDB مع توضيح القصة والطاقم والتصنيف والتريلر عند توفره. تساعد الصفحة على فهم أجواء الفيلم قبل الانتقال إلى المشاهدة.",
    "sources": {
      "tmdb": "https://www.themoviedb.org/movie/1115191"
    }
  }
}
